saveToCsvfile/saveToCsv.py
saveToCsvfile-1.0.0.dist-info/LICENSE.txt
saveToCsvfile-1.0.0.dist-info/METADATA
saveToCsvfile-1.0.0.dist-info/WHEEL
saveToCsvfile-1.0.0.dist-info/top_level.txt
saveToCsvfile-1.0.0.dist-info/RECORD
